cropnet/__init__.py
cropnet/data_downloader.py
cropnet/data_retriever.py
cropnet/dataset/__init__.py
cropnet/dataset/hrrr_computed_dataset.py
cropnet/dataset/sentinel2_imagery.py
cropnet/dataset/usda_crop_dataset.py
cropnet/utils/__init__.py
cropnet/utils/download_USDA.py
cropnet/utils/download_sentinel.py
cropnet/utils/download_wrf.py
cropnet/utils/extract_wrf_data.py
cropnet/utils/geo_grid_recent.py
cropnet/utils/geo_utils.py
cropnet/utils/path_utils.py
cropnet/utils/supplementary/__init__.py
cropnet/utils/supplementary/geo_grid_recent.py
dataset/__init__.py
dataset/hrrr_computed_dataset.py
dataset/sentinel2_imagery.py
dataset/usda_crop_dataset.py
cropnet-0.2.0.dist-info/METADATA
cropnet-0.2.0.dist-info/WHEEL
cropnet-0.2.0.dist-info/top_level.txt
cropnet-0.2.0.dist-info/RECORD
