Metadata-Version: 2.1
Name: cropnet
Version: 0.2.0
Summary: A Python package for the CropNet dataset
Author: Anonymous AI4Science
Author-email: anonymous.ai4science@gmail.com
License: Free for non-commercial use
Classifier: Development Status :: 3 - Alpha
Classifier: Intended Audience :: Science/Research
Classifier: License :: Free for non-commercial use
Classifier: Operating System :: MacOS
Classifier: Operating System :: POSIX :: Linux
Classifier: Programming Language :: Python :: 3.8
Classifier: Programming Language :: Python :: 3.9
Classifier: Programming Language :: Python :: 3.10
Requires-Dist: torch (>=1.13.0)
Requires-Dist: torchvision (>=0.14.0)
Requires-Dist: numpy (>=1.24.4)
Requires-Dist: pandas (>=2.0.3)
Requires-Dist: h5py (>=3.9.0)
Requires-Dist: Pillow (>=10.0.0)
Requires-Dist: einops (>=0.6.1)
Requires-Dist: scikit-learn (>=1.3.0)
Requires-Dist: matplotlib (>=3.7.2)
Requires-Dist: oauthlib (>=3.2.2)
Requires-Dist: requests-oauthlib (>=1.3.1)
Requires-Dist: geopandas (>=0.13.2)
Requires-Dist: shapely (>=2.0.1)
Requires-Dist: tqdm (>=4.65.0)
Requires-Dist: herbie-data (>=2023.3.0)
